pi_touch_gui/__init__.py
pi_touch_gui/colors.py
pi_touch_gui/gui.py
pi_touch_gui/widgets.py
pi_touch_gui/multitouch/__init__.py
pi_touch_gui/multitouch/ft5406.py
pi_touch_gui/multitouch/hp4ts.py
pi_touch_gui/multitouch/raspberrypi_ts.py
pi_touch_pi_touch_gui-0.1.0.dist-info/METADATA
pi_touch_pi_touch_gui-0.1.0.dist-info/WHEEL
pi_touch_pi_touch_gui-0.1.0.dist-info/top_level.txt
pi_touch_pi_touch_gui-0.1.0.dist-info/RECORD
