Metadata-Version: 2.1
Name: pi-touch-pi-touch-gui
Version: 0.1.0
Summary: A graphic UI optimized for touch screens
Home-page: https://github.com/EdwinWiseOne/PiTouchGui
Author: Edwin Wise
Author-email: edwin@simreal.com
License: UNKNOWN
Platform: UNKNOWN
Classifier: Development Status :: 3 - Alpha
Classifier: Intended Audience :: Developers
Classifier: Topic :: Software Development :: Libraries
Requires-Python: >=3.6
Requires-Dist: pygame
